{"nodes": [{"id": "c_xampp_htdocs_dairyfarm_js_schedules_js", "label": "schedules.js", "file_type": "code", "source_file": "C:\\xampp\\htdocs\\dairyfarm\\js\\schedules.js", "source_location": "L1"}, {"id": "js_schedules_updatepagination", "label": "updatePagination()", "file_type": "code", "source_file": "C:\\xampp\\htdocs\\dairyfarm\\js\\schedules.js", "source_location": "L46"}, {"id": "js_schedules_updatecurrentpencount", "label": "updateCurrentPenCount()", "file_type": "code", "source_file": "C:\\xampp\\htdocs\\dairyfarm\\js\\schedules.js", "source_location": "L130"}], "edges": [{"source": "c_xampp_htdocs_dairyfarm_js_schedules_js", "target": "js_schedules_updatepagination", "relation": "contains", "confidence": "EXTRACTED", "source_file": "C:\\xampp\\htdocs\\dairyfarm\\js\\schedules.js", "source_location": "L46", "weight": 1.0}, {"source": "c_xampp_htdocs_dairyfarm_js_schedules_js", "target": "js_schedules_updatecurrentpencount", "relation": "contains", "confidence": "EXTRACTED", "source_file": "C:\\xampp\\htdocs\\dairyfarm\\js\\schedules.js", "source_location": "L130", "weight": 1.0}], "raw_calls": [{"caller_nid": "js_schedules_updatepagination", "callee": "info", "is_member_call": true, "source_file": "C:\\xampp\\htdocs\\dairyfarm\\js\\schedules.js", "source_location": "L47"}, {"caller_nid": "js_schedules_updatepagination", "callee": "text", "is_member_call": true, "source_file": "C:\\xampp\\htdocs\\dairyfarm\\js\\schedules.js", "source_location": "L48"}, {"caller_nid": "js_schedules_updatepagination", "callee": "$", "is_member_call": false, "source_file": "C:\\xampp\\htdocs\\dairyfarm\\js\\schedules.js", "source_location": "L48"}, {"caller_nid": "js_schedules_updatepagination", "callee": "html", "is_member_call": true, "source_file": "C:\\xampp\\htdocs\\dairyfarm\\js\\schedules.js", "source_location": "L56"}, {"caller_nid": "js_schedules_updatepagination", "callee": "$", "is_member_call": false, "source_file": "C:\\xampp\\htdocs\\dairyfarm\\js\\schedules.js", "source_location": "L56"}, {"caller_nid": "js_schedules_updatepagination", "callee": "prop", "is_member_call": true, "source_file": "C:\\xampp\\htdocs\\dairyfarm\\js\\schedules.js", "source_location": "L58"}, {"caller_nid": "js_schedules_updatepagination", "callee": "$", "is_member_call": false, "source_file": "C:\\xampp\\htdocs\\dairyfarm\\js\\schedules.js", "source_location": "L58"}, {"caller_nid": "js_schedules_updatepagination", "callee": "prop", "is_member_call": true, "source_file": "C:\\xampp\\htdocs\\dairyfarm\\js\\schedules.js", "source_location": "L59"}, {"caller_nid": "js_schedules_updatepagination", "callee": "$", "is_member_call": false, "source_file": "C:\\xampp\\htdocs\\dairyfarm\\js\\schedules.js", "source_location": "L59"}, {"caller_nid": "js_schedules_updatecurrentpencount", "callee": "find", "is_member_call": true, "source_file": "C:\\xampp\\htdocs\\dairyfarm\\js\\schedules.js", "source_location": "L131"}, {"caller_nid": "js_schedules_updatecurrentpencount", "callee": "find", "is_member_call": true, "source_file": "C:\\xampp\\htdocs\\dairyfarm\\js\\schedules.js", "source_location": "L132"}, {"caller_nid": "js_schedules_updatecurrentpencount", "callee": "filter", "is_member_call": true, "source_file": "C:\\xampp\\htdocs\\dairyfarm\\js\\schedules.js", "source_location": "L133"}, {"caller_nid": "js_schedules_updatecurrentpencount", "callee": "text", "is_member_call": true, "source_file": "C:\\xampp\\htdocs\\dairyfarm\\js\\schedules.js", "source_location": "L136"}, {"caller_nid": "js_schedules_updatecurrentpencount", "callee": "text", "is_member_call": true, "source_file": "C:\\xampp\\htdocs\\dairyfarm\\js\\schedules.js", "source_location": "L138"}, {"caller_nid": "js_schedules_updatecurrentpencount", "callee": "text", "is_member_call": true, "source_file": "C:\\xampp\\htdocs\\dairyfarm\\js\\schedules.js", "source_location": "L140"}]}